README.rst
setup.py
pros/__init__.py
pros/cli.py
pros/logger.py
pros/utils.py
pros.egg-info/PKG-INFO
pros.egg-info/SOURCES.txt
pros.egg-info/dependency_links.txt
pros.egg-info/top_level.txt
pros/commands/__init__.py
pros/commands/combines.py
pros/commands/decoders.py
pros/commands/encoders.py
pros/commands/extractors.py
pros/commands/filters.py
pros/commands/generators.py
pros/commands/hashers.py
pros/commands/inputs.py
pros/commands/outputs.py
pros/commands/reducers.py
pros/commands/transforms.py
pros/core/__init__.py
pros/core/catalog.py
pros/core/chain.py
pros/core/command.py
pros/core/loader.py
pros/core/root.py
pros/core/template.py
pros/core/tree.py